httpx_extensions/__init__.py
httpx_extensions/__version__.py
httpx_extensions/client.py
httpx_extensions/mock.py
httpx_extensions/models.py
httpx_extensions/py.typed
httpx_extensions/transport.py
httpx_extensions/httpcore/__init__.py
httpx_extensions/httpcore/pool.py
httpx_extensions/httpcore/proxy.py
httpx_extensions/httpcore/socks.py
httpx_extensions-0.1.1.dist-info/LICENSE.md
httpx_extensions-0.1.1.dist-info/METADATA
httpx_extensions-0.1.1.dist-info/WHEEL
httpx_extensions-0.1.1.dist-info/top_level.txt
httpx_extensions-0.1.1.dist-info/RECORD
